{
  "project_info": {
    "project_number": "753484460169",
    "project_id": "p17-gestionstockmedicame-def67",
    "storage_bucket": "p17-gestionstockmedicame-def67.firebasestorage.app"
  },
  "client": [
    {
      "client_info": {
        "mobilesdk_app_id": "1:753484460169:android:fcd64ebda8543aaef89658",
        "android_client_info": {
          "package_name": "com.openclassrooms.rebonnte"
        }
      },
      "oauth_client": [
        {
          "client_id": "753484460169-u1k86gjaackd6t9gi33h6cmug8aikneh.apps.googleusercontent.com",
          "client_type": 1,
          "android_info": {
            "package_name": "com.openclassrooms.rebonnte",
            "certificate_hash": "ad1868805cc37bdef6adf1593c09ee68bae54aa7"
          }
        },
        {
          "client_id": "753484460169-bv5u01o2s6tctaed6p8sg6vv1hqhq700.apps.googleusercontent.com",
          "client_type": 3
        }
      ],
      "api_key": [
        {
          "current_key": "AIzaSyDfXGwkRxc8XLTnrezR8y2FzRqkS9ZCdLk"
        }
      ],
      "services": {
        "appinvite_service": {
          "other_platform_oauth_client": [
            {
              "client_id": "753484460169-bv5u01o2s6tctaed6p8sg6vv1hqhq700.apps.googleusercontent.com",
              "client_type": 3
            }
          ]
        }
      }
    }
  ],
  "configuration_version": "1"
}